frequenz/channels/__init__.py
frequenz/channels/_anycast.py
frequenz/channels/_broadcast.py
frequenz/channels/_exceptions.py
frequenz/channels/_generic.py
frequenz/channels/_latest_value_cache.py
frequenz/channels/_merge.py
frequenz/channels/_receiver.py
frequenz/channels/_select.py
frequenz/channels/_sender.py
frequenz/channels/conftest.py
frequenz/channels/event.py
frequenz/channels/file_watcher.py
frequenz/channels/py.typed
frequenz/channels/timer.py
frequenz/channels/experimental/__init__.py
frequenz/channels/experimental/_grouping_latest_value_cache.py
frequenz/channels/experimental/_nop_receiver.py
frequenz/channels/experimental/_optional_receiver.py
frequenz/channels/experimental/_pipe.py
frequenz/channels/experimental/_relay_sender.py
frequenz/channels/experimental/_with_previous.py
frequenz_channels-1.10.0.dist-info/licenses/LICENSE
frequenz_channels-1.10.0.dist-info/METADATA
frequenz_channels-1.10.0.dist-info/WHEEL
frequenz_channels-1.10.0.dist-info/top_level.txt
frequenz_channels-1.10.0.dist-info/RECORD
